labelf_api/__init__.py
labelf_api/client.py
labelf_api/exceptions.py
tests/__init__.py
tests/test_client.py
labelf_api-0.1.1.dist-info/METADATA
labelf_api-0.1.1.dist-info/WHEEL
labelf_api-0.1.1.dist-info/top_level.txt
labelf_api-0.1.1.dist-info/RECORD
